vizpanel/__init__.py
vizpanel/main.py
vizpanel/vizpanel.py
vizpanel/web/index.html
vizpanel-0.1.0.dist-info/METADATA
vizpanel-0.1.0.dist-info/WHEEL
vizpanel-0.1.0.dist-info/entry_points.txt
vizpanel-0.1.0.dist-info/licenses/LICENSE
vizpanel-0.1.0.dist-info/RECORD
